jinja_try_catch/__init__.py
jinja_try_catch/extension.py
jinja_try_catch-0.1.1.dist-info/LICENSE
jinja_try_catch-0.1.1.dist-info/METADATA
jinja_try_catch-0.1.1.dist-info/WHEEL
jinja_try_catch-0.1.1.dist-info/RECORD
