Metadata-Version: 2.1
Name: jinja-try-catch
Version: 0.1.1
Summary: Jinja2 extension adding {% try %} {% catch %} exception handling
Home-page: https://github.com/RewstApp/jinja-try-catch
License: MIT
Author: Zach Kanzler
Author-email: zach@rewst.io
Requires-Python: >=3.7
Classifier: Development Status :: 4 - Beta
Classifier: Environment :: Web Environment
Classifier: Intended Audience :: Developers
Classifier: License :: OSI Approved :: MIT License
Classifier: Operating System :: OS Independent
Classifier: Programming Language :: Python
Classifier: Programming Language :: Python :: 3
Classifier: Programming Language :: Python :: 3.7
Classifier: Programming Language :: Python :: 3.8
Classifier: Programming Language :: Python :: 3.9
Classifier: Programming Language :: Python :: 3.10
Classifier: Programming Language :: Python :: 3.11
Classifier: Topic :: Internet :: WWW/HTTP :: Dynamic Content
Classifier: Topic :: Text Processing :: Markup :: HTML
Requires-Dist: Jinja2 (>=3.0.0)
Project-URL: Repository, https://github.com/RewstApp/jinja-try-catch
